labdiscoverylib/__init__.py
labdiscoverylib/config.py
labdiscoverylib/exc.py
labdiscoverylib/ops.py
labdiscoverylib/tasks.py
labdiscoverylib/users.py
labdiscoverylib/utils.py
labdiscoverylib/views.py
labdiscoverylib/backends/__init__.py
labdiscoverylib/backends/redis_manager.py
labdiscoverylib-0.6.0.dist-info/LICENSE
labdiscoverylib-0.6.0.dist-info/METADATA
labdiscoverylib-0.6.0.dist-info/WHEEL
labdiscoverylib-0.6.0.dist-info/top_level.txt
labdiscoverylib-0.6.0.dist-info/RECORD
