Metadata-Version: 2.1
Name: labdiscoverylib
Version: 0.6.0
Summary: LabDiscoveryEngine library for creating unmanaged laboratories
Home-page: https://developers.labsland.com/labdiscoverylib/
Author: LabsLand
Author-email: dev@labsland.com
License: GNU AGPL v3
Project-URL: Documentation, https://developers.labsland.com/labdiscoverylib/en/stable/
Project-URL: Code, https://github.com/labsland/labdiscoverylib
Project-URL: Issue tracker, https://github.com/labsland/labdiscoverylib/issues
Platform: UNKNOWN
Classifier: Development Status :: 4 - Beta
Classifier: Environment :: Web Environment
Classifier: Intended Audience :: Developers
Classifier: License :: OSI Approved :: GNU Affero General Public License v3
Classifier: Operating System :: OS Independent
Classifier: Programming Language :: Python
Classifier: Programming Language :: Python :: 3
Classifier: Programming Language :: Python :: 3.8
Classifier: Programming Language :: Python :: 3.9
Classifier: Programming Language :: Python :: 3.10
Classifier: Programming Language :: Python :: 3.11
Classifier: Topic :: Education
Classifier: Topic :: Internet :: WWW/HTTP
Classifier: Topic :: Software Development :: Libraries :: Application Frameworks
License-File: LICENSE
Requires-Dist: flask (<3)
Requires-Dist: redis
Requires-Dist: requests
Requires-Dist: six
Requires-Dist: werkzeug (<3)
